aws_toolbelt-0.1.0.dist-info/METADATA
aws_toolbelt-0.1.0.dist-info/WHEEL
aws_toolbelt-0.1.0.dist-info/entry_points.txt
aws_toolbelt/__init__.py
aws_toolbelt/main.py
aws_toolbelt/style.css
aws_toolbelt-0.1.0.dist-info/RECORD
